mag/.python-version
mag/__init__.py
mag/__version__.py
mag/core.py
mag/main.py
mag/mcp_client.py
mag/app/.gitignore
mag/app/__init__.py
mag/app/api/__init__.py
mag/app/api/chat_routes.py
mag/app/api/graph_gen_routes.py
mag/app/api/graph_import_export_routes.py
mag/app/api/graph_routes.py
mag/app/api/mcp_routes.py
mag/app/api/model_routes.py
mag/app/api/prompt_routes.py
mag/app/api/routes.py
mag/app/api/system_routes.py
mag/app/core/__init__.py
mag/app/core/config.py
mag/app/core/file_manager.py
mag/app/core/minio_client.py
mag/app/models/__init__.py
mag/app/models/chat_schema.py
mag/app/models/graph_schema.py
mag/app/models/mcp_schema.py
mag/app/models/model_schema.py
mag/app/models/prompt_schema.py
mag/app/services/__init__.py
mag/app/services/chat_service.py
mag/app/services/graph_service.py
mag/app/services/mcp_service.py
mag/app/services/model_service.py
mag/app/services/mongodb_service.py
mag/app/services/prompt_service.py
mag/app/services/chat/__init__.py
mag/app/services/chat/message_builder.py
mag/app/services/chat/prompts.py
mag/app/services/docdb/__init__.py
mag/app/services/docdb/chat_manager.py
mag/app/services/docdb/conversation_manager.py
mag/app/services/docdb/graph_manager.py
mag/app/services/docdb/graph_run_manager.py
mag/app/services/docdb/mcp_manager.py
mag/app/services/graph/__init__.py
mag/app/services/graph/ai_graph_generator.py
mag/app/services/graph/background_executor.py
mag/app/services/graph/conversation_manager.py
mag/app/services/graph/graph_executor.py
mag/app/services/graph/graph_processor.py
mag/app/services/mcp/__init__.py
mag/app/services/mcp/ai_mcp_generator.py
mag/app/services/mcp/client_manager.py
mag/app/services/mcp/server_manager.py
mag/app/services/mcp/tool_executor.py
mag/app/services/prompt/__init__.py
mag/app/services/prompt/prompt_manager.py
mag/app/templates/__init__.py
mag/app/templates/flow_diagram.py
mag/app/templates/mcp_generator_template.md
mag/app/templates/mcp_sequential_template.py
mcp_agent_graph-3.0.0.dist-info/METADATA
mcp_agent_graph-3.0.0.dist-info/WHEEL
mcp_agent_graph-3.0.0.dist-info/licenses/LICENSE
mcp_agent_graph-3.0.0.dist-info/RECORD
