Metadata-Version: 2.4
Name: mcp-agent-graph
Version: 3.0.0
Summary: MCP Agent Graph - Python SDK for Agent Development Framework
Project-URL: Documentation, https://github.com/keta1930/mcp-agent-graph#readme
Project-URL: Issues, https://github.com/keta1930/mcp-agent-graph/issues
Project-URL: Source, https://github.com/keta1930/mcp-agent-graph
Author-email: Yan Yixin <yandeheng1@gmail.com>
License-Expression: Apache-2.0
License-File: LICENSE
Keywords: agent,ai,framework,graph,mcp
Classifier: Development Status :: 4 - Beta
Classifier: Intended Audience :: Developers
Classifier: License :: OSI Approved :: Apache Software License
Classifier: Programming Language :: Python :: 3
Classifier: Programming Language :: Python :: 3.11
Classifier: Topic :: Software Development :: Libraries
Classifier: Topic :: Software Development :: Libraries :: Application Frameworks
Requires-Python: >=3.11
Requires-Dist: aiohttp
Requires-Dist: asyncio==3.4.3
Requires-Dist: bs4
Requires-Dist: fastapi
Requires-Dist: fastmcp==2.8
Requires-Dist: langchain
Requires-Dist: matplotlib
Requires-Dist: mcp[cli]==1.9.4
Requires-Dist: minio>=7.2.16
Requires-Dist: motor>=3.7.1
Requires-Dist: notebook
Requires-Dist: numpy
Requires-Dist: openai
Requires-Dist: pandas
Requires-Dist: pydantic
Requires-Dist: python-multipart>=0.0.20
Requires-Dist: pyzmq
Requires-Dist: requests
Requires-Dist: starlette>=0.46.2
Requires-Dist: tqdm
Requires-Dist: typing-extensions
Requires-Dist: uvicorn
Requires-Dist: websockets
